CHANGELOG.rst
README.rst
cans/__init__.py
cans/py.typed
cans-0.1.3.dist-info/LICENSE
cans-0.1.3.dist-info/WHEEL
cans-0.1.3.dist-info/METADATA
cans-0.1.3.dist-info/RECORD
