Metadata-Version: 2.1
Name: cans
Version: 0.1.3
Summary: Robust, composable, functional containers
Home-page: https://github.com/ariebovenberg/cans
License: MIT
Author: Arie Bovenberg
Author-email: a.c.bovenberg@gmail.com
Requires-Python: >=3.6,<4.0
Classifier: Development Status :: 4 - Beta
Classifier: License :: OSI Approved :: MIT License
Classifier: Programming Language :: Python :: 3
Classifier: Programming Language :: Python :: 3.10
Classifier: Programming Language :: Python :: 3.6
Classifier: Programming Language :: Python :: 3.7
Classifier: Programming Language :: Python :: 3.8
Classifier: Programming Language :: Python :: 3.9
Classifier: Topic :: Software Development :: Libraries :: Python Modules
Classifier: Typing :: Typed
Requires-Dist: dataclasses (>=0.8,<0.9); python_version < "3.7"
Requires-Dist: importlib-metadata (>=1.0,<2.0); python_version < "3.8"
Requires-Dist: typing-extensions (>=3.7.4,<4.0.0)
Project-URL: Repository, https://github.com/ariebovenberg/cans
